README
setup.cfg
setup.py
src/clusto_ec2.egg-info/PKG-INFO
src/clusto_ec2.egg-info/SOURCES.txt
src/clusto_ec2.egg-info/dependency_links.txt
src/clusto_ec2.egg-info/entry_points.txt
src/clusto_ec2.egg-info/not-zip-safe
src/clusto_ec2.egg-info/pbr.json
src/clusto_ec2.egg-info/requires.txt
src/clusto_ec2.egg-info/top_level.txt
src/clustoec2/__init__.py
src/clustoec2/commands/__init__.py
src/clustoec2/commands/bootstrap.py
src/clustoec2/commands/ec2.py
src/clustoec2/commands/vpc.py
src/clustoec2/drivers/__init__.py
src/clustoec2/drivers/base.py
src/clustoec2/drivers/categories/__init__.py
src/clustoec2/drivers/categories/securitygroup.py
src/clustoec2/drivers/devices/__init__.py
src/clustoec2/drivers/devices/servers/__init__.py
src/clustoec2/drivers/devices/servers/ec2server.py
src/clustoec2/drivers/devices/servers/vpcserver.py
src/clustoec2/drivers/locations/__init__.py
src/clustoec2/drivers/locations/datacenters/__init__.py
src/clustoec2/drivers/locations/datacenters/ec2region.py
src/clustoec2/drivers/locations/datacenters/vpc.py
src/clustoec2/drivers/locations/zones/__init__.py
src/clustoec2/drivers/locations/zones/ec2zone.py
src/clustoec2/drivers/locations/zones/subnet.py
src/clustoec2/drivers/resourcemanagers/__init__.py
src/clustoec2/drivers/resourcemanagers/ec2connmanager.py
src/clustoec2/drivers/resourcemanagers/vpcconnmanager.py