Metadata-Version: 1.0
Name: clusto-ec2
Version: 0.6.4
Summary: Amazon EC2 extension for clusto
Home-page: UNKNOWN
Author: Ron Gorodetzky
Author-email: ron@parktree.net
License: UNKNOWN
Platform: UNKNOWN
